falcon_sqlalchemy/__init__.py
falcon_sqlalchemy/hooks.py
falcon_sqlalchemy/jsonencoder.py
falcon_sqlalchemy/resource.py
falcon_sqlalchemy/types.py
falcon_sqlalchemy/util.py
falcon_sqlalchemy-0.3.dist-info/DESCRIPTION.rst
falcon_sqlalchemy-0.3.dist-info/METADATA
falcon_sqlalchemy-0.3.dist-info/RECORD
falcon_sqlalchemy-0.3.dist-info/WHEEL
falcon_sqlalchemy-0.3.dist-info/metadata.json
falcon_sqlalchemy-0.3.dist-info/top_level.txt
