Metadata-Version: 2.0
Name: falcon-sqlalchemy
Version: 0.3
Summary: Falcon extension to easily use SQLAlchemy
Home-page: https://github.com/vixcess/falcon-sqlalchemy
Author: Shiqiao Du
Author-email: lucidfrontier.45@gmail.com
License: Apache License version 2
Platform: UNKNOWN
Classifier: Programming Language :: Python :: 3.4
Classifier: Programming Language :: Python :: 3.5
Classifier: Programming Language :: Python :: 3.6
Requires-Dist: chainson (>=0.2)
Requires-Dist: falcon
Requires-Dist: jsonschema
Requires-Dist: sqlalchemy
Requires-Dist: toolz
